nekodl/__init__.py
nekodl/animesama/__init__.py
nekodl/animesama/download.py
nekodl/animesama/fetch.py
nekodl/animesama/info.py
nekodl/bilibili/__init__.py
nekodl/bilibili/download.py
nekodl/bilibili/fetch.py
nekodl/bilibili/info.py
nekodl/bilibili/utils.py
nekodl/core/__init__.py
nekodl/core/core.py
nekodl/core/utils.py
nekodl/spotify/__init__.py
nekodl/spotify/download.py
nekodl/spotify/fetch.py
nekodl/spotify/info.py
nekodl/spotify/utils.py
nekodl/tiktok/__init__.py
nekodl/tiktok/download.py
nekodl/tiktok/fetch.py
nekodl/tiktok/info.py
nekodl/youtube/__init__.py
nekodl/youtube/download.py
nekodl/youtube/fetch.py
nekodl/youtube/info.py
nekodl-0.1.11.dist-info/licenses/LICENSE
nekodl-0.1.11.dist-info/METADATA
nekodl-0.1.11.dist-info/WHEEL
nekodl-0.1.11.dist-info/top_level.txt
nekodl-0.1.11.dist-info/RECORD
