Metadata-Version: 2.4
Name: NekoDL
Version: 0.1.11
Summary: Unified media downloader (YouTube, TikTok, AnimeSama)
Author: TMCooper
License: MIT
Requires-Python: >=3.11
License-File: LICENSE
Requires-Dist: yt-dlp
Requires-Dist: spotdl
Requires-Dist: requests
Dynamic: license-file
